speedruncomapi/__init__.py
speedruncomapi-0.0.31.dist-info/METADATA
speedruncomapi-0.0.31.dist-info/WHEEL
speedruncomapi-0.0.31.dist-info/top_level.txt
speedruncomapi-0.0.31.dist-info/RECORD
