Metadata-Version: 2.1
Name: speedruncomapi
Version: 0.0.31
Summary: A Python API wrapper for Speedrun.com
Author: Sallie Lay
Author-email: mail@neuralnine.com
Keywords: python,wrapper,api,speedrun
Classifier: Programming Language :: Python :: 3
Classifier: Operating System :: Unix
Classifier: Operating System :: MacOS :: MacOS X
Classifier: Operating System :: Microsoft :: Windows
Requires-Dist: requests
